[
    {
        "tau": 0.0,
        "r": 1.0,
        "epsilon": 0.8345204457387541,
        "epsilon (in hartree)": 0.8345204457387541
    },
    {
        "tau": 0.0,
        "r": 2.0,
        "epsilon": 0.2877113379492546,
        "epsilon (in hartree)": 0.2877113379492546
    },
    {
        "tau": 0.0,
        "r": 5.0,
        "epsilon": 0.13150718177279883,
        "epsilon (in hartree)": 0.13150718177279883
    },
    {
        "tau": 0.0,
        "r": 7.0,
        "epsilon": 0.187444069025984,
        "epsilon (in hartree)": 0.187444069025984
    },
    {
        "tau": 0.0,
        "r": 10.0,
        "epsilon": 0.26687039228199727,
        "epsilon (in hartree)": 0.26687039228199727
    },
    {
        "tau": 0.0,
        "r": 15.0,
        "epsilon": Infinity,
        "epsilon (in hartree)": Infinity
    },
    {
        "tau": 0.0,
        "r": 20.0,
        "epsilon": Infinity,
        "epsilon (in hartree)": Infinity
    },
    {
        "tau": 5.0,
        "r": 1.0,
        "epsilon": -2.8438027664818235,
        "epsilon (in hartree)": -2.8438027664818235
    },
    {
        "tau": 5.0,
        "r": 2.0,
        "epsilon": Infinity,
        "epsilon (in hartree)": Infinity
    },
    {
        "tau": 5.0,
        "r": 5.0,
        "epsilon": Infinity,
        "epsilon (in hartree)": Infinity
    },
    {
        "tau": 5.0,
        "r": 7.0,
        "epsilon": Infinity,
        "epsilon (in hartree)": Infinity
    },
    {
        "tau": 5.0,
        "r": 10.0,
        "epsilon": Infinity,
        "epsilon (in hartree)": Infinity
    },
    {
        "tau": 5.0,
        "r": 15.0,
        "epsilon": Infinity,
        "epsilon (in hartree)": Infinity
    },
    {
        "tau": 5.0,
        "r": 20.0,
        "epsilon": Infinity,
        "epsilon (in hartree)": Infinity
    },
    {
        "tau": 10.0,
        "r": 1.0,
        "epsilon": -9.43838662187401,
        "epsilon (in hartree)": -9.43838662187401
    },
    {
        "tau": 10.0,
        "r": 2.0,
        "epsilon": Infinity,
        "epsilon (in hartree)": Infinity
    },
    {
        "tau": 10.0,
        "r": 5.0,
        "epsilon": Infinity,
        "epsilon (in hartree)": Infinity
    },
    {
        "tau": 10.0,
        "r": 7.0,
        "epsilon": Infinity,
        "epsilon (in hartree)": Infinity
    },
    {
        "tau": 10.0,
        "r": 10.0,
        "epsilon": Infinity,
        "epsilon (in hartree)": Infinity
    },
    {
        "tau": 10.0,
        "r": 15.0,
        "epsilon": Infinity,
        "epsilon (in hartree)": Infinity
    },
    {
        "tau": 10.0,
        "r": 20.0,
        "epsilon": Infinity,
        "epsilon (in hartree)": Infinity
    }
]